{
  "type": "orderWsDTO",
  "appliedOrderPromotions": [],
  "appliedProductPromotions": [],
  "appliedVouchers": [],
  "calculated": true,
  "code": "00000006",
  "deliveryAddress": {
    "country": {
      "isocode": "GB"
    },
    "firstName": "Kore",
    "formattedAddress": "test, test, test, 123456789, United Kingdom",
    "id": "8796125888535",
    "lastName": "Test",
    "line1": "test",
    "line2": "test",
    "postalCode": "123456789",
    "town": "test"
  },
  "deliveryCost": {
    "currencyIso": "GBP",
    "formattedValue": "£5.99",
    "priceType": "BUY",
    "value": 5.99
  },
  "deliveryItemsQuantity": 3,
  "deliveryMode": {
    "code": "standard-gross",
    "deliveryCost": {
      "currencyIso": "GBP",
      "formattedValue": "£5.99",
      "priceType": "BUY",
      "value": 5.99
    },
    "description": "3-5 business days",
    "name": "Standard Delivery"
  },
  "deliveryOrderGroups": [
    {
      "entries": [
        {
          "entryNumber": 0,
          "product": {
            "availableForPickup": true,
            "baseProduct": "122320_kelly",
            "code": "300737425",
            "name": "Eclipse Tee SS kelly XS",
            "purchasable": true,
            "stock": {
              "stockLevel": 11
            },
            "url": "/Categories/Streetwear-men/T-Shirts-men/Eclipse-Tee-SS/p/300737425"
          },
          "quantity": 1,
          "totalPrice": {
            "currencyIso": "GBP",
            "value": 24.26
          }
        },
        {
          "entryNumber": 1,
          "product": {
            "availableForPickup": true,
            "baseProduct": "122333_palm",
            "code": "300737506",
            "name": "Because Tee SS palm M",
            "purchasable": true,
            "stock": {
              "stockLevel": 6
            },
            "url": "/Categories/Streetwear-men/T-Shirts-men/Because-Tee-SS/p/300737506"
          },
          "quantity": 1,
          "totalPrice": {
            "currencyIso": "GBP",
            "value": 28.31
          }
        },
        {
          "entryNumber": 2,
          "product": {
            "availableForPickup": true,
            "baseProduct": "122340_marine_heather",
            "code": "300613369",
            "name": "Jackson Tee SS marine heather L",
            "purchasable": true,
            "stock": {
              "stockLevel": 18
            },
            "url": "/Categories/Streetwear-men/T-Shirts-men/Jackson-Tee-SS/p/300613369"
          },
          "quantity": 1,
          "totalPrice": {
            "currencyIso": "GBP",
            "value": 30.74
          }
        }
      ],
      "totalPriceWithTax": {
        "currencyIso": "GBP",
        "formattedValue": "£83.31",
        "priceType": "BUY",
        "value": 83.31
      }
    }
  ],
  "entries": [
    {
      "entryNumber": 0,
      "product": {
        "availableForPickup": true,
        "baseProduct": "122320_kelly",
        "code": "300737425",
        "name": "Eclipse Tee SS kelly XS",
        "purchasable": true,
        "stock": {
          "stockLevel": 11
        },
        "url": "/Categories/Streetwear-men/T-Shirts-men/Eclipse-Tee-SS/p/300737425"
      },
      "quantity": 1,
      "totalPrice": {
        "currencyIso": "GBP",
        "value": 24.26
      }
    },
    {
      "entryNumber": 1,
      "product": {
        "availableForPickup": true,
        "baseProduct": "122333_palm",
        "code": "300737506",
        "name": "Because Tee SS palm M",
        "purchasable": true,
        "stock": {
          "stockLevel": 6
        },
        "url": "/Categories/Streetwear-men/T-Shirts-men/Because-Tee-SS/p/300737506"
      },
      "quantity": 1,
      "totalPrice": {
        "currencyIso": "GBP",
        "value": 28.31
      }
    },
    {
      "entryNumber": 2,
      "product": {
        "availableForPickup": true,
        "baseProduct": "122340_marine_heather",
        "code": "300613369",
        "name": "Jackson Tee SS marine heather L",
        "purchasable": true,
        "stock": {
          "stockLevel": 18
        },
        "url": "/Categories/Streetwear-men/T-Shirts-men/Jackson-Tee-SS/p/300613369"
      },
      "quantity": 1,
      "totalPrice": {
        "currencyIso": "GBP",
        "value": 30.74
      }
    }
  ],
  "guid": "d29a4243-1a4f-4917-9b48-eca2072d9f3f",
  "net": false,
  "orderDiscounts": {
    "currencyIso": "GBP",
    "formattedValue": "£0.00",
    "priceType": "BUY",
    "value": 0
  },
  "paymentInfo": {
    "accountHolderName": "Jim Murphy",
    "billingAddress": {
      "country": {
        "isocode": "GB"
      },
      "firstName": "Kore",
      "formattedAddress": "test, test, test, 123456789, United Kingdom",
      "id": "8796125954071",
      "lastName": "Test",
      "line1": "test",
      "line2": "test",
      "postalCode": "123456789",
      "town": "test"
    },
    "cardNumber": "************1111",
    "cardType": {
      "code": "visa",
      "name": "Visa"
    },
    "defaultPayment": false,
    "expiryMonth": "1",
    "expiryYear": "2020",
    "id": "8796093087786",
    "saved": true,
    "subscriptionId": "b5c6425b-3d04-4e4e-a883-d57d063e16ee"
  },
  "pickupItemsQuantity": 0,
  "pickupOrderGroups": [],
  "productDiscounts": {
    "currencyIso": "GBP",
    "formattedValue": "£0.00",
    "priceType": "BUY",
    "value": 0
  },
  "site": "apparel-uk",
  "store": "apparel-uk",
  "subTotal": {
    "currencyIso": "GBP",
    "formattedValue": "£83.31",
    "priceType": "BUY",
    "value": 83.31
  },
  "totalDiscounts": {
    "currencyIso": "GBP",
    "formattedValue": "£0.00",
    "priceType": "BUY",
    "value": 0
  },
  "totalItems": 3,
  "totalPrice": {
    "currencyIso": "GBP",
    "formattedValue": "£89.30",
    "priceType": "BUY",
    "value": 89.3
  },
  "totalPriceWithTax": {
    "currencyIso": "GBP",
    "formattedValue": "£89.30",
    "priceType": "BUY",
    "value": 89.3
  },
  "totalTax": {
    "currencyIso": "GBP",
    "formattedValue": "£0.00",
    "priceType": "BUY",
    "value": 0
  },
  "user": {
    "name": "Kore Test",
    "uid": "kstream001@gmail.com"
  },
  "consignments": [
    {
      "code": "cons00000006_0",
      "deliveryPointOfService": {
        "address": {
          "country": {
            "isocode": "GB"
          },
          "formattedAddress": "70 Queen Street, Cardiff, G51 2QU, United Kingdom",
          "id": "8796097871895",
          "line2": "70 Queen Street",
          "postalCode": "G51 2QU",
          "town": "Cardiff"
        },
        "displayName": "Warehouse West",
        "geoPoint": {
          "latitude": 51.4820862,
          "longitude": -3.1755472
        },
        "name": "ap_warehouse_w"
      },
      "entries": [
        {
          "orderEntry": {
            "entryNumber": 2,
            "product": {
              "availableForPickup": true,
              "baseProduct": "122340_marine_heather",
              "code": "300613369",
              "name": "Jackson Tee SS marine heather L",
              "purchasable": true,
              "stock": {
                "stockLevel": 18
              },
              "url": "/Categories/Streetwear-men/T-Shirts-men/Jackson-Tee-SS/p/300613369"
            },
            "quantity": 1,
            "totalPrice": {
              "currencyIso": "GBP",
              "value": 30.74
            }
          },
          "quantity": 1
        },
        {
          "orderEntry": {
            "entryNumber": 1,
            "product": {
              "availableForPickup": true,
              "baseProduct": "122333_palm",
              "code": "300737506",
              "name": "Because Tee SS palm M",
              "purchasable": true,
              "stock": {
                "stockLevel": 6
              },
              "url": "/Categories/Streetwear-men/T-Shirts-men/Because-Tee-SS/p/300737506"
            },
            "quantity": 1,
            "totalPrice": {
              "currencyIso": "GBP",
              "value": 28.31
            }
          },
          "quantity": 1
        }
      ],
      "shippingAddress": {
        "country": {
          "isocode": "GB"
        },
        "firstName": "Kore",
        "formattedAddress": "test, test, test, 123456789, United Kingdom",
        "id": "8796125888535",
        "lastName": "Test",
        "line1": "test",
        "line2": "test",
        "postalCode": "123456789",
        "town": "test"
      },
      "status": "READY"
    },
    {
      "code": "cons00000006_1",
      "deliveryPointOfService": {
        "address": {
          "country": {
            "isocode": "DE"
          },
          "formattedAddress": "Arabellastraße 5, 81925, München, Germany",
          "id": "8796097806359",
          "line2": "Arabellastraße 5",
          "postalCode": "81925",
          "town": "München"
        },
        "displayName": "Warehouse South",
        "geoPoint": {
          "latitude": 48.15149,
          "longitude": 11.61823
        },
        "name": "ap_warehouse_s"
      },
      "entries": [
        {
          "orderEntry": {
            "entryNumber": 0,
            "product": {
              "availableForPickup": true,
              "baseProduct": "122320_kelly",
              "code": "300737425",
              "name": "Eclipse Tee SS kelly XS",
              "purchasable": true,
              "stock": {
                "stockLevel": 11
              },
              "url": "/Categories/Streetwear-men/T-Shirts-men/Eclipse-Tee-SS/p/300737425"
            },
            "quantity": 1,
            "totalPrice": {
              "currencyIso": "GBP",
              "value": 24.26
            }
          },
          "quantity": 1
        }
      ],
      "shippingAddress": {
        "country": {
          "isocode": "GB"
        },
        "firstName": "Kore",
        "formattedAddress": "test, test, test, 123456789, United Kingdom",
        "id": "8796125888535",
        "lastName": "Test",
        "line1": "test",
        "line2": "test",
        "postalCode": "123456789",
        "town": "test"
      },
      "status": "READY"
    }
  ],
  "created": "2016-11-02T16:28:04+0000",
  "guestCustomer": false,
  "status": "READY",
  "statusDisplay": "processing",
  "unconsignedEntries": []
}